{
    "source": "github",
    "owner": "jillix",
    "name": "bind-cart",
    "dependencies": [
        "/main.js",
        "/cart.js",
        "/twbs-input-number.js",
        "http://ajax.googleapis.com/ajax/libs/jquery/1/jquery.min.js",
        "github/jillix/bind/v0.1.0",
        "github/jillix/events/v0.1.1"
    ],
    "operations": [
        { "file": "operations.js", "function": "create" },
        { "file": "operations.js", "function": "read" },
        { "file": "operations.js", "function": "update" },
        { "file": "operations.js", "function": "remove" },
        { "file": "operations.js", "function": "computeCosts" },
        { "file": "operations.js", "function": "checkout" }
    ]
}
